{
  "group_code": "hk-secondary-s5-geography",
  "source": {
    "type": "curriculum_style_public_references",
    "references": [
      "EDB Geography Curriculum and Assessment Guide (Secondary 4-6)",
      "EDB senior secondary Geography elective learning objectives",
      "Public Hong Kong S5 Geography syllabus topic examples (advanced urban systems, planning and governance, transport sustainability, atmospheric and climate dynamics, fluvial and coastal geomorphology, slope and tectonic hazards, disaster risk reduction, population and migration, industrial location and economic change, ecosystem conservation, Pearl River Delta regional studies, GIS and HKDSE evaluation skills)"
    ],
    "note": "No fixed official Hong Kong S5 geography vocabulary list is prescribed; this list is theme-based for senior secondary S5 geography enrichment import. Term-only entries are completed during import."
  },
  "themes": {
    "hkdse-advanced-fieldwork-and-geographic-inquiry": [
      "geographic inquiry cycle",
      "research design in geography",
      "fieldwork hypothesis testing",
      "systematic sampling method",
      "stratified sampling method",
      "questionnaire reliability",
      "interview validity",
      "field measurement accuracy",
      "GPS and GIS field mapping",
      "transect survey method",
      "land use transect",
      "environmental quality index",
      "traffic count survey",
      "pedestrian flow survey",
      "primary data limitation",
      "secondary data limitation",
      "statistical analysis in geography",
      "evaluate fieldwork conclusion",
      "ethical fieldwork practice",
      "communicate geographic investigation",
      "HKDSE fieldwork examination skill"
    ],
    "megacity-urban-change-and-spatial-inequality": [
      "megacity growth pattern",
      "primate city dominance",
      "urban hierarchy system",
      "urban sprawl consequence",
      "suburbanization trend analysis",
      "counter-urbanization process",
      "gentrification social impact",
      "urban renewal displacement",
      "inner city deprivation",
      "urban poverty concentration",
      "spatial inequality pattern",
      "housing affordability crisis",
      "informal settlement growth",
      "urban segregation pattern",
      "urban heat island intensification",
      "urban microclimate change",
      "comparing megacity challenges",
      "evaluating urban inequality policy",
      "urban sustainability indicator",
      "urban transformation case study",
      "quality of urban life debate"
    ],
    "urban-planning-policy-and-land-governance": [
      "urban planning governance",
      "zoning policy implementation",
      "outline zoning plan revision",
      "town planning approval process",
      "public consultation outcome",
      "land use conflict resolution",
      "brownfield regeneration project",
      "greenfield development impact",
      "green belt policy debate",
      "land reclamation environmental impact",
      "high density housing strategy",
      "public housing allocation policy",
      "heritage conservation conflict",
      "urban design quality standard",
      "smart city governance model",
      "participatory planning mechanism",
      "comparing planning frameworks",
      "evaluating planning effectiveness",
      "land governance transparency",
      "urban policy trade-off analysis",
      "planning for climate resilience"
    ],
    "transport-planning-mobility-and-sustainability": [
      "integrated transport planning",
      "mass transit capacity planning",
      "road network expansion debate",
      "traffic demand management",
      "congestion pricing policy",
      "public transport fare policy",
      "modal shift strategy",
      "private car restraint policy",
      "low emission zone policy",
      "cycling network expansion",
      "walkability urban design",
      "intermodal connectivity",
      "freight transport planning",
      "transport carbon footprint",
      "transport equity analysis",
      "accessibility for disabled people",
      "comparing transport policy models",
      "evaluating sustainable mobility plan",
      "transport and land use integration",
      "transport infrastructure financing",
      "future mobility technology impact"
    ],
    "atmospheric-circulation-and-weather-dynamics": [
      "global atmospheric circulation",
      "Hadley cell circulation",
      "Ferrel cell circulation",
      "Polar cell circulation",
      "Coriolis force effect",
      "jet stream influence",
      "monsoon seasonal mechanism",
      "El Nino Southern Oscillation",
      "La Nina event impact",
      "air mass modification",
      "frontogenesis process",
      "cyclogenesis process",
      "anticyclone weather pattern",
      "orographic precipitation mechanism",
      "convectional storm development",
      "tropical cyclone track forecasting",
      "extreme rainfall forecasting",
      "comparing weather hazard types",
      "interpreting synoptic chart",
      "evaluate weather forecast accuracy",
      "weather-climate system link"
    ],
    "climate-change-impacts-and-policy-responses": [
      "anthropogenic climate change",
      "greenhouse gas concentration trend",
      "enhanced greenhouse effect mechanism",
      "global warming evidence",
      "climate change impact assessment",
      "sea level rise projection",
      "coastal inundation risk",
      "extreme heat event increase",
      "extreme rainfall intensification",
      "climate mitigation policy",
      "climate adaptation planning",
      "net zero emission target",
      "carbon trading mechanism",
      "renewable energy policy mix",
      "climate resilient infrastructure",
      "international climate agreement",
      "local climate action plan",
      "comparing climate policy approaches",
      "evaluating mitigation effectiveness",
      "climate justice debate",
      "climate change and urban vulnerability"
    ],
    "fluvial-systems-and-integrated-flood-management": [
      "fluvial geomorphology system",
      "river channel morphology",
      "river energy gradient",
      "hydraulic geometry relationship",
      "sediment load transport",
      "channel migration process",
      "flood frequency analysis",
      "return period of flood",
      "flood risk mapping",
      "integrated flood management",
      "upstream catchment management",
      "downstream floodplain zoning",
      "reservoir flood attenuation",
      "levee and floodwall design",
      "river channelization debate",
      "natural flood management",
      "afforestation in catchment",
      "comparing flood management strategies",
      "evaluating flood control project",
      "human activity and flood risk",
      "climate change and flood regime"
    ],
    "coastal-systems-and-marine-environment-management": [
      "coastal sediment cell concept",
      "wave energy and erosion",
      "wave refraction at coast",
      "headland erosion landform",
      "longshore drift sediment transport",
      "spit and tombolo formation",
      "barrier island coast",
      "salt marsh accretion",
      "mangrove coastal protection",
      "coral reef bleaching threat",
      "coastal erosion acceleration",
      "coastal submergence trend",
      "storm surge inundation",
      "hard coastal engineering",
      "soft coastal engineering",
      "integrated coastal zone management",
      "marine pollution monitoring",
      "comparing coastal management cases",
      "evaluating coastal protection scheme",
      "coastal hazard risk assessment",
      "sea level rise coastal impact"
    ],
    "slope-processes-and-landslide-risk-reduction": [
      "slope geomorphology analysis",
      "factor of safety on slope",
      "slope material strength",
      "pore water pressure effect",
      "rainfall intensity trigger",
      "vegetation root reinforcement",
      "human slope cutting impact",
      "road cutting slope hazard",
      "debris flow runout zone",
      "rockfall trajectory zone",
      "landslide susceptibility map",
      "landslide warning criterion",
      "slope drainage system design",
      "slope retaining structure",
      "slope maintenance programme",
      "community landslide education",
      "comparing slope hazard cases",
      "evaluating slope stabilization work",
      "landslide disaster response",
      "climate change and slope instability",
      "risk-based slope management"
    ],
    "plate-tectonics-seismic-and-volcanic-hazards": [
      "plate boundary classification",
      "convergent boundary process",
      "divergent boundary process",
      "transform boundary process",
      "subduction zone earthquake",
      "intraplate earthquake",
      "seismic wave propagation",
      "earthquake magnitude measurement",
      "earthquake intensity measurement",
      "tsunami warning system",
      "volcanic eruption prediction",
      "volcanic hazard zone mapping",
      "Ring of Fire tectonic setting",
      "earthquake resistant building code",
      "seismic retrofitting technology",
      "early warning system technology",
      "comparing tectonic hazard regions",
      "evaluating seismic risk reduction",
      "volcanic hazard preparedness",
      "tectonic hazard and development planning",
      "plate tectonics theory evidence"
    ],
    "integrated-natural-hazard-and-disaster-management": [
      "multi-hazard risk assessment",
      "hazard exposure mapping",
      "social vulnerability index",
      "disaster risk reduction framework",
      "Sendai Framework principle",
      "disaster preparedness planning",
      "emergency response coordination",
      "disaster recovery planning",
      "build back better principle",
      "community resilience building",
      "early warning dissemination",
      "evacuation planning standard",
      "disaster relief logistics",
      "insurance and hazard risk",
      "climate-related hazard amplification",
      "comparing disaster case studies",
      "evaluating disaster management performance",
      "hazard education programme",
      "international disaster cooperation",
      "risk communication strategy",
      "integrated hazard governance"
    ],
    "population-migration-and-demographic-geography": [
      "population distribution pattern",
      "population density variation",
      "demographic transition stage",
      "population pyramid interpretation",
      "aging population challenge",
      "youth bulge population",
      "dependency ratio analysis",
      "natural increase trend",
      "rural-urban migration flow",
      "international migration corridor",
      "refugee migration crisis",
      "forced migration cause",
      "migration policy regulation",
      "brain drain phenomenon",
      "remittance economic impact",
      "population policy evaluation",
      "comparing demographic structures",
      "evaluating migration policy",
      "population and resource pressure",
      "urbanization and migration link",
      "demographic data forecasting"
    ],
    "industrial-location-and-economic-transformation": [
      "industrial location theory",
      "Weber locational triangle",
      "agglomeration economy benefit",
      "industrial estate planning",
      "science and technology park",
      "industrial relocation driver",
      "deindustrialization process",
      "offshore manufacturing shift",
      "global value chain",
      "special economic zone function",
      "free port trade advantage",
      "service sector dominance",
      "financial services cluster",
      "logistics hub development",
      "tourism industry geography",
      "economic restructuring impact",
      "comparing industrial regions",
      "evaluating industrial policy",
      "globalization and local economy",
      "technology and industrial change",
      "industrial pollution management"
    ],
    "ecosystem-services-and-conservation-management": [
      "ecosystem service classification",
      "biodiversity conservation priority",
      "habitat fragmentation impact",
      "ecological corridor design",
      "protected area network planning",
      "country park management system",
      "marine protected area policy",
      "wetland Ramsar site protection",
      "invasive species management",
      "deforestation driver analysis",
      "reforestation programme evaluation",
      "pollution impact on ecosystem",
      "environmental impact assessment process",
      "ecological restoration technique",
      "sustainable tourism carrying capacity",
      "community-based conservation",
      "comparing conservation models",
      "evaluating conservation effectiveness",
      "ecosystem service economic value",
      "human-wildlife conflict management",
      "conservation and development balance"
    ],
    "pearl-river-delta-regional-studies-and-hong-kong": [
      "Pearl River Delta region",
      "Greater Bay Area integration",
      "cross-boundary transport network",
      "cross-boundary economic link",
      "Hong Kong financial centre role",
      "Hong Kong logistics hub role",
      "Hong Kong tourism geography",
      "Hong Kong housing geography",
      "Hong Kong land supply debate",
      "Hong Kong waste management challenge",
      "Hong Kong water supply source",
      "Hong Kong air quality trend",
      "Hong Kong slope hazard profile",
      "Hong Kong coastal vulnerability",
      "Hong Kong climate action plan",
      "regional urban system comparison",
      "comparing PRD city development",
      "evaluating regional integration impact",
      "Hong Kong regional competitiveness",
      "Hong Kong sustainable development debate",
      "Hong Kong geographic future scenario"
    ],
    "gis-spatial-analysis-and-hkdse-evaluation-skills": [
      "advanced GIS analysis",
      "spatial autocorrelation concept",
      "hotspot analysis method",
      "buffer analysis application",
      "network analysis in transport",
      "digital terrain analysis",
      "change detection analysis",
      "remote sensing time series",
      "LiDAR topographic mapping",
      "spatial decision support system",
      "map projection distortion",
      "scale effect in mapping",
      "data visualization in geography",
      "cross-topic geographic synthesis",
      "cause-process-impact explanation",
      "evaluate geographic model",
      "compare case study regions",
      "structured geography essay",
      "data-based question skill",
      "source-based question skill",
      "HKDSE geography evaluation synthesis"
    ]
  }
}
