{
  "group_code": "hk-secondary-s2-mathematics",
  "source": {
    "type": "curriculum_style_public_references",
    "references": [
      "EDB Mathematics Education Key Learning Area Curriculum Guide (Secondary 1-3)",
      "EDB junior secondary Mathematics curriculum framework: Number and Algebra, Measures Shape and Space, Data Handling",
      "Public Hong Kong Secondary 2 Mathematics syllabus topic examples (indices, factorization, simultaneous equations, quadratic functions, Pythagoras, trigonometry, circle geometry, similarity, statistics, probability)"
    ],
    "note": "No fixed official Hong Kong S2 mathematics vocabulary list is prescribed; this list is theme-based for S2 mathematics enrichment import. Term-only entries are completed during import."
  },
  "themes": {
    "indices-and-powers": [
      "index law",
      "law of indices",
      "power",
      "exponent",
      "base",
      "negative index",
      "fractional index",
      "zero index",
      "product of powers",
      "quotient of powers",
      "power of a power",
      "scientific notation",
      "standard form",
      "surd",
      "like surd",
      "rationalize",
      "rationalizing denominator",
      "simplify powers"
    ],
    "algebraic-manipulation": [
      "algebraic expression",
      "expand",
      "factorize",
      "common factor",
      "difference of two squares",
      "perfect square trinomial",
      "cross method",
      "algebraic fraction",
      "simplify algebraic fraction",
      "cross multiply",
      "lowest terms",
      "numerator",
      "denominator",
      "like term",
      "collect like terms",
      "substitution",
      "change of subject",
      "subject of formula",
      "formula rearrangement"
    ],
    "linear-equations-and-inequalities": [
      "linear inequality",
      "inequality symbol",
      "number line",
      "solution set",
      "simultaneous linear equations",
      "substitution method",
      "elimination method",
      "graphical method",
      "intersection point",
      "consistent equations",
      "inconsistent equations",
      "word problem",
      "form an equation",
      "check solution",
      "verify"
    ],
    "quadratic-expressions-and-functions": [
      "quadratic expression",
      "quadratic equation",
      "parabola",
      "vertex",
      "turning point",
      "axis of symmetry",
      "maximum value",
      "minimum value",
      "x-intercept",
      "y-intercept",
      "root of equation",
      "zero of function",
      "complete the square",
      "quadratic formula",
      "discriminant",
      "graph of quadratic function",
      "coefficient of x squared",
      "opening upward",
      "opening downward"
    ],
    "proportion-rates-and-variation": [
      "direct proportion",
      "inverse proportion",
      "joint variation",
      "constant of proportionality",
      "ratio",
      "rate",
      "unit rate",
      "scale",
      "map scale",
      "speed",
      "density",
      "pressure",
      "exchange rate",
      "percentage change",
      "compound interest",
      "simple interest",
      "profit margin",
      "mark-up",
      "discount rate"
    ],
    "pythagoras-and-trigonometry": [
      "right-angled triangle",
      "hypotenuse",
      "opposite side",
      "adjacent side",
      "sine",
      "cosine",
      "tangent",
      "trigonometric ratio",
      "SOHCAHTOA",
      "angle of elevation",
      "angle of depression",
      "bearing",
      "three-figure bearing",
      "solve triangle",
      "find unknown side",
      "find unknown angle",
      "trigonometric table",
      "calculator mode"
    ],
    "circle-geometry": [
      "circle",
      "radius",
      "diameter",
      "circumference",
      "arc",
      "chord",
      "tangent",
      "point of contact",
      "centre of circle",
      "angle at centre",
      "angle at circumference",
      "angle in semicircle",
      "cyclic quadrilateral",
      "opposite angles in cyclic quadrilateral",
      "alternate segment",
      "tangent-radius property",
      "concentric circles",
      "minor arc",
      "major arc",
      "sector",
      "segment"
    ],
    "similarity-and-congruence": [
      "similar triangle",
      "similarity test",
      "scale factor",
      "enlargement",
      "reduction",
      "corresponding angle",
      "corresponding side",
      "ratio of areas",
      "ratio of volumes",
      "congruent triangle",
      "congruence test",
      "side-angle-side",
      "angle-side-angle",
      "side-side-side",
      "right angle-hypotenuse-side"
    ],
    "transformations-and-symmetry": [
      "transformation",
      "reflection",
      "rotation",
      "translation",
      "enlargement",
      "image",
      "object",
      "invariant point",
      "invariant line",
      "centre of rotation",
      "centre of enlargement",
      "mirror line",
      "vector",
      "column vector",
      "line symmetry",
      "rotational symmetry",
      "order of rotational symmetry"
    ],
    "mensuration-advanced": [
      "arc length",
      "area of sector",
      "surface area",
      "curved surface area",
      "lateral surface area",
      "volume of prism",
      "volume of cylinder",
      "volume of cone",
      "volume of pyramid",
      "volume of sphere",
      "hemisphere",
      "frustum",
      "cross section",
      "net of solid",
      "composite solid",
      "compound shape",
      "unit conversion",
      "square unit",
      "cubic unit"
    ],
    "coordinate-geometry": [
      "coordinate plane",
      "Cartesian plane",
      "ordered pair",
      "x-coordinate",
      "y-coordinate",
      "midpoint",
      "distance between two points",
      "distance formula",
      "equation of straight line",
      "y-intercept form",
      "point-slope form",
      "parallel line",
      "perpendicular line",
      "intersect",
      "region",
      "plot point",
      "gradient-intercept form"
    ],
    "statistics-and-data-handling": [
      "data set",
      "raw data",
      "grouped data",
      "frequency",
      "frequency table",
      "frequency polygon",
      "cumulative frequency",
      "cumulative frequency curve",
      "ogive",
      "quartile",
      "lower quartile",
      "upper quartile",
      "interquartile range",
      "percentile",
      "five-number summary",
      "outlier",
      "average",
      "weighted mean",
      "standard deviation",
      "variance",
      "correlation",
      "positive correlation",
      "negative correlation",
      "no correlation",
      "line of best fit",
      "trend",
      "interpretation"
    ],
    "probability-and-chance": [
      "random experiment",
      "trial",
      "outcome",
      "event",
      "sample space",
      "equally likely",
      "theoretical probability",
      "experimental probability",
      "relative frequency",
      "tree diagram",
      "combined event",
      "independent event",
      "dependent event",
      "mutually exclusive",
      "without replacement",
      "with replacement",
      "conditional probability",
      "expected value",
      "fair",
      "biased"
    ],
    "mathematical-reasoning-and-problem-solving": [
      "problem solving",
      "reasoning",
      "proof",
      "deduce",
      "justify",
      "conjecture",
      "counterexample",
      "theorem",
      "definition",
      "property",
      "assumption",
      "diagram",
      "sketch",
      "strategy",
      "method",
      "working",
      "solution steps",
      "interpret result",
      "reasonableness",
      "estimate",
      "approximation",
      "significant figure",
      "round off",
      "upper bound",
      "lower bound"
    ]
  }
}
