{
  "group_code": "hk-secondary-s1-integrated-science",
  "terms": {
    "hypothesis": {
      "status": "complete",
      "missing": [],
      "errors": {},
      "completed_at": "2026-06-21T00:38:34Z"
    },
    "variable": {
      "status": "incomplete",
      "missing": [
        "pronunciation",
        "part_of_speech"
      ],
      "errors": {},
      "completed_at": null
    },
    "observe": {
      "status": "complete",
      "missing": [],
      "errors": {},
      "completed_at": "2026-06-21T00:38:36Z"
    },
    "mixture": {
      "status": "incomplete",
      "missing": [
        "pronunciation",
        "part_of_speech"
      ],
      "errors": {},
      "completed_at": null
    },
    "solution": {
      "status": "complete",
      "missing": [],
      "errors": {},
      "completed_at": "2026-06-21T00:38:38Z"
    },
    "dissolve": {
      "status": "incomplete",
      "missing": [
        "pronunciation",
        "part_of_speech"
      ],
      "errors": {},
      "completed_at": null
    },
    "evaporation": {
      "status": "incomplete",
      "missing": [
        "pronunciation",
        "part_of_speech"
      ],
      "errors": {},
      "completed_at": null
    },
    "condensation": {
      "status": "complete",
      "missing": [],
      "errors": {},
      "completed_at": "2026-06-21T00:38:41Z"
    },
    "density": {
      "status": "incomplete",
      "missing": [
        "pronunciation",
        "part_of_speech"
      ],
      "errors": {},
      "completed_at": null
    },
    "conduct": {
      "status": "complete",
      "missing": [],
      "errors": {},
      "completed_at": "2026-06-21T00:38:42Z"
    },
    "insulator": {
      "status": "incomplete",
      "missing": [
        "pronunciation",
        "part_of_speech"
      ],
      "errors": {},
      "completed_at": null
    },
    "ecosystem": {
      "status": "incomplete",
      "missing": [
        "pronunciation",
        "part_of_speech"
      ],
      "errors": {},
      "completed_at": null
    },
    "producer": {
      "status": "incomplete",
      "missing": [
        "pronunciation",
        "part_of_speech"
      ],
      "errors": {},
      "completed_at": null
    },
    "consumer": {
      "status": "incomplete",
      "missing": [
        "pronunciation",
        "part_of_speech"
      ],
      "errors": {},
      "completed_at": null
    },
    "decomposer": {
      "status": "incomplete",
      "missing": [
        "pronunciation",
        "part_of_speech"
      ],
      "errors": {},
      "completed_at": null
    },
    "photosynthesis": {
      "status": "incomplete",
      "missing": [
        "pronunciation",
        "part_of_speech"
      ],
      "errors": {},
      "completed_at": null
    },
    "respiration": {
      "status": "incomplete",
      "missing": [
        "pronunciation",
        "part_of_speech"
      ],
      "errors": {},
      "completed_at": null
    },
    "magnify": {
      "status": "incomplete",
      "missing": [
        "pronunciation",
        "part_of_speech"
      ],
      "errors": {},
      "completed_at": null
    },
    "safety goggles": {
      "status": "incomplete",
      "missing": [
        "pronunciation",
        "part_of_speech"
      ],
      "errors": {},
      "completed_at": null
    },
    "accurate": {
      "status": "complete",
      "missing": [],
      "errors": {},
      "completed_at": "2026-06-21T00:38:51Z"
    }
  }
}
