{
  "group_code": "hk-secondary-s4-economics",
  "terms": {
    "opportunity cost": {
      "status": "incomplete",
      "missing": [
        "pronunciation",
        "part_of_speech"
      ],
      "errors": {},
      "completed_at": null
    },
    "scarcity": {
      "status": "incomplete",
      "missing": [
        "pronunciation",
        "part_of_speech"
      ],
      "errors": {},
      "completed_at": null
    },
    "marginal benefit": {
      "status": "incomplete",
      "missing": [
        "pronunciation",
        "part_of_speech"
      ],
      "errors": {},
      "completed_at": null
    },
    "diminishing returns": {
      "status": "incomplete",
      "missing": [
        "pronunciation",
        "part_of_speech"
      ],
      "errors": {},
      "completed_at": null
    },
    "elasticity of demand": {
      "status": "incomplete",
      "missing": [
        "pronunciation",
        "part_of_speech"
      ],
      "errors": {},
      "completed_at": null
    },
    "substitute goods": {
      "status": "incomplete",
      "missing": [
        "pronunciation",
        "part_of_speech"
      ],
      "errors": {},
      "completed_at": null
    },
    "complementary goods": {
      "status": "incomplete",
      "missing": [
        "pronunciation",
        "part_of_speech"
      ],
      "errors": {},
      "completed_at": null
    },
    "fixed costs": {
      "status": "incomplete",
      "missing": [
        "pronunciation",
        "part_of_speech"
      ],
      "errors": {},
      "completed_at": null
    },
    "average total cost": {
      "status": "incomplete",
      "missing": [
        "pronunciation",
        "part_of_speech"
      ],
      "errors": {},
      "completed_at": null
    },
    "economies of scale": {
      "status": "incomplete",
      "missing": [
        "pronunciation",
        "part_of_speech"
      ],
      "errors": {
        "last": "Expected ',' or '}' after property value in JSON at position 228 (line 10 column 23)"
      },
      "completed_at": null
    },
    "perfect competition": {
      "status": "incomplete",
      "missing": [
        "pronunciation",
        "part_of_speech"
      ],
      "errors": {},
      "completed_at": null
    },
    "monopoly": {
      "status": "incomplete",
      "missing": [
        "pronunciation",
        "part_of_speech"
      ],
      "errors": {
        "last": "Expected ',' or '}' after property value in JSON at position 32 (line 2 column 31)"
      },
      "completed_at": null
    },
    "oligopoly": {
      "status": "incomplete",
      "missing": [
        "pronunciation",
        "part_of_speech"
      ],
      "errors": {},
      "completed_at": null
    },
    "barriers to entry": {
      "status": "incomplete",
      "missing": [
        "pronunciation",
        "part_of_speech"
      ],
      "errors": {},
      "completed_at": null
    },
    "gross domestic product (gdp)": {
      "status": "incomplete",
      "missing": [
        "pronunciation",
        "part_of_speech"
      ],
      "errors": {},
      "completed_at": null
    },
    "inflation": {
      "status": "incomplete",
      "missing": [
        "pronunciation",
        "part_of_speech"
      ],
      "errors": {},
      "completed_at": null
    },
    "unemployment rate": {
      "status": "incomplete",
      "missing": [
        "pronunciation",
        "part_of_speech"
      ],
      "errors": {},
      "completed_at": null
    },
    "fiscal policy": {
      "status": "incomplete",
      "missing": [
        "pronunciation",
        "part_of_speech"
      ],
      "errors": {},
      "completed_at": null
    },
    "monetary policy": {
      "status": "incomplete",
      "missing": [
        "pronunciation",
        "part_of_speech"
      ],
      "errors": {},
      "completed_at": null
    },
    "balance of payments": {
      "status": "incomplete",
      "missing": [
        "pronunciation",
        "part_of_speech"
      ],
      "errors": {},
      "completed_at": null
    }
  }
}
