{
  "group_code": "hk-secondary-s6-mathematics",
  "terms": {
    "differentiation": {
      "status": "complete",
      "missing": [],
      "errors": {},
      "completed_at": "2026-06-25T12:10:04Z"
    },
    "integration": {
      "status": "complete",
      "missing": [],
      "errors": {},
      "completed_at": "2026-06-25T12:10:05Z"
    },
    "binomial expansion": {
      "status": "complete",
      "missing": [],
      "errors": {},
      "completed_at": "2026-06-25T12:10:05Z"
    },
    "partial fractions": {
      "status": "complete",
      "missing": [],
      "errors": {},
      "completed_at": "2026-06-25T12:10:06Z"
    },
    "parametric equations": {
      "status": "complete",
      "missing": [],
      "errors": {},
      "completed_at": "2026-06-25T12:10:06Z"
    },
    "normal distribution": {
      "status": "complete",
      "missing": [],
      "errors": {},
      "completed_at": "2026-06-25T12:10:07Z"
    },
    "hypothesis testing": {
      "status": "complete",
      "missing": [],
      "errors": {},
      "completed_at": "2026-06-25T12:10:07Z"
    },
    "correlation coefficient": {
      "status": "complete",
      "missing": [],
      "errors": {},
      "completed_at": "2026-06-25T12:10:08Z"
    },
    "vector product": {
      "status": "complete",
      "missing": [],
      "errors": {},
      "completed_at": "2026-06-25T12:10:08Z"
    },
    "scalar product": {
      "status": "complete",
      "missing": [],
      "errors": {},
      "completed_at": "2026-06-25T12:10:09Z"
    },
    "complex numbers": {
      "status": "complete",
      "missing": [],
      "errors": {},
      "completed_at": "2026-06-25T12:10:10Z"
    },
    "modulus": {
      "status": "complete",
      "missing": [],
      "errors": {},
      "completed_at": "2026-06-25T12:10:10Z"
    },
    "amplitude": {
      "status": "complete",
      "missing": [],
      "errors": {},
      "completed_at": "2026-06-25T12:10:11Z"
    },
    "periodicity": {
      "status": "complete",
      "missing": [],
      "errors": {},
      "completed_at": "2026-06-25T12:10:11Z"
    },
    "inverse trigonometric functions": {
      "status": "complete",
      "missing": [],
      "errors": {},
      "completed_at": "2026-06-25T12:10:12Z"
    },
    "limit": {
      "status": "complete",
      "missing": [],
      "errors": {},
      "completed_at": "2026-06-21T00:51:34Z"
    },
    "continuity": {
      "status": "complete",
      "missing": [],
      "errors": {},
      "completed_at": "2026-06-25T12:10:12Z"
    },
    "stationary point": {
      "status": "complete",
      "missing": [],
      "errors": {},
      "completed_at": "2026-06-25T12:10:13Z"
    },
    "standard deviation": {
      "status": "complete",
      "missing": [],
      "errors": {},
      "completed_at": "2026-06-25T12:10:13Z"
    },
    "conditional probability": {
      "status": "complete",
      "missing": [],
      "errors": {},
      "completed_at": "2026-06-25T12:10:14Z"
    },
    "acceleration": {
      "status": "complete",
      "missing": [],
      "errors": {},
      "completed_at": "2026-06-25T20:25:47Z"
    },
    "accumulation": {
      "status": "complete",
      "missing": [],
      "errors": {},
      "completed_at": "2026-06-25T12:11:18Z"
    },
    "addition of vectors": {
      "status": "complete",
      "missing": [],
      "errors": {},
      "completed_at": "2026-06-25T12:11:18Z"
    },
    "addition rule": {
      "status": "complete",
      "missing": [],
      "errors": {},
      "completed_at": "2026-06-25T12:11:19Z"
    },
    "alternative hypothesis": {
      "status": "complete",
      "missing": [],
      "errors": {},
      "completed_at": "2026-06-25T12:11:19Z"
    },
    "angle between vectors": {
      "status": "complete",
      "missing": [],
      "errors": {},
      "completed_at": "2026-06-25T12:12:01Z"
    },
    "antiderivative": {
      "status": "complete",
      "missing": [],
      "errors": {},
      "completed_at": "2026-06-25T12:12:52Z"
    },
    "approximation": {
      "status": "complete",
      "missing": [],
      "errors": {},
      "completed_at": "2026-06-25T12:13:07Z"
    },
    "arccos": {
      "status": "complete",
      "missing": [],
      "errors": {},
      "completed_at": "2026-06-25T12:14:18Z"
    },
    "arcsin": {
      "status": "complete",
      "missing": [],
      "errors": {},
      "completed_at": "2026-06-25T12:15:37Z"
    },
    "arctan": {
      "status": "complete",
      "missing": [],
      "errors": {},
      "completed_at": "2026-06-25T12:16:44Z"
    },
    "area between curves": {
      "status": "complete",
      "missing": [],
      "errors": {},
      "completed_at": "2026-06-25T12:16:45Z"
    },
    "area under curve": {
      "status": "complete",
      "missing": [],
      "errors": {},
      "completed_at": "2026-06-25T12:16:45Z"
    },
    "argand diagram": {
      "status": "complete",
      "missing": [],
      "errors": {},
      "completed_at": "2026-06-25T12:19:47Z"
    },
    "argument of complex number": {
      "status": "complete",
      "missing": [],
      "errors": {},
      "completed_at": "2026-06-25T12:22:34Z"
    },
    "arithmetic series": {
      "status": "complete",
      "missing": [],
      "errors": {},
      "completed_at": "2026-06-25T12:22:35Z"
    },
    "assumption": {
      "status": "complete",
      "missing": [],
      "errors": {},
      "completed_at": "2026-06-25T12:22:35Z"
    },
    "asymptote": {
      "status": "complete",
      "missing": [],
      "errors": {},
      "completed_at": "2026-06-25T12:22:36Z"
    },
    "base case": {
      "status": "complete",
      "missing": [],
      "errors": {},
      "completed_at": "2026-06-25T12:24:00Z"
    },
    "bayes theorem": {
      "status": "complete",
      "missing": [],
      "errors": {},
      "completed_at": "2026-06-25T12:24:58Z"
    },
    "binomial distribution": {
      "status": "complete",
      "missing": [],
      "errors": {},
      "completed_at": "2026-06-25T12:24:59Z"
    },
    "box-and-whisker plot": {
      "status": "complete",
      "missing": [],
      "errors": {},
      "completed_at": "2026-06-25T12:24:59Z"
    },
    "chain rule": {
      "status": "complete",
      "missing": [],
      "errors": {},
      "completed_at": "2026-06-25T12:25:00Z"
    },
    "change of base": {
      "status": "complete",
      "missing": [],
      "errors": {},
      "completed_at": "2026-06-25T12:25:00Z"
    },
    "chi-square test": {
      "status": "complete",
      "missing": [],
      "errors": {},
      "completed_at": "2026-06-25T12:26:12Z"
    },
    "column vector": {
      "status": "complete",
      "missing": [],
      "errors": {},
      "completed_at": "2026-06-25T12:26:12Z"
    },
    "complex conjugate": {
      "status": "complete",
      "missing": [],
      "errors": {},
      "completed_at": "2026-06-25T12:27:31Z"
    },
    "composite function": {
      "status": "complete",
      "missing": [],
      "errors": {},
      "completed_at": "2026-06-25T12:27:32Z"
    },
    "compound angle formula": {
      "status": "complete",
      "missing": [],
      "errors": {},
      "completed_at": "2026-06-25T12:28:36Z"
    },
    "concave down": {
      "status": "complete",
      "missing": [],
      "errors": {},
      "completed_at": "2026-06-25T12:29:37Z"
    },
    "concave up": {
      "status": "complete",
      "missing": [],
      "errors": {},
      "completed_at": "2026-06-25T12:31:20Z"
    },
    "confidence interval": {
      "status": "complete",
      "missing": [],
      "errors": {},
      "completed_at": "2026-06-25T12:32:23Z"
    },
    "conic section": {
      "status": "complete",
      "missing": [],
      "errors": {},
      "completed_at": "2026-06-25T12:32:24Z"
    },
    "conjecture": {
      "status": "complete",
      "missing": [],
      "errors": {},
      "completed_at": "2026-06-25T12:32:24Z"
    },
    "continuity correction": {
      "status": "complete",
      "missing": [],
      "errors": {},
      "completed_at": "2026-06-25T12:34:50Z"
    },
    "continuous random variable": {
      "status": "complete",
      "missing": [],
      "errors": {},
      "completed_at": "2026-06-25T12:35:31Z"
    },
    "converge": {
      "status": "complete",
      "missing": [],
      "errors": {},
      "completed_at": "2026-06-25T12:36:23Z"
    },
    "coordinate plane": {
      "status": "complete",
      "missing": [],
      "errors": {},
      "completed_at": "2026-06-25T12:36:24Z"
    },
    "correlation": {
      "status": "complete",
      "missing": [],
      "errors": {},
      "completed_at": "2026-06-25T12:36:25Z"
    },
    "cosine graph": {
      "status": "complete",
      "missing": [],
      "errors": {},
      "completed_at": "2026-06-25T12:37:24Z"
    },
    "counterexample": {
      "status": "complete",
      "missing": [],
      "errors": {},
      "completed_at": "2026-06-25T12:37:24Z"
    },
    "cramer's rule": {
      "status": "complete",
      "missing": [],
      "errors": {},
      "completed_at": "2026-06-25T12:39:15Z"
    },
    "critical region": {
      "status": "complete",
      "missing": [],
      "errors": {},
      "completed_at": "2026-06-25T12:39:15Z"
    },
    "cross product": {
      "status": "complete",
      "missing": [],
      "errors": {},
      "completed_at": "2026-06-25T12:40:20Z"
    },
    "de moivre theorem": {
      "status": "complete",
      "missing": [],
      "errors": {},
      "completed_at": "2026-06-25T12:41:28Z"
    },
    "decay model": {
      "status": "complete",
      "missing": [],
      "errors": {},
      "completed_at": "2026-06-25T12:42:43Z"
    },
    "deduce": {
      "status": "complete",
      "missing": [],
      "errors": {},
      "completed_at": "2026-06-25T12:42:43Z"
    },
    "definite integral": {
      "status": "complete",
      "missing": [],
      "errors": {},
      "completed_at": "2026-06-25T12:42:44Z"
    },
    "definition": {
      "status": "complete",
      "missing": [],
      "errors": {},
      "completed_at": "2026-06-25T12:42:45Z"
    },
    "derivative": {
      "status": "complete",
      "missing": [],
      "errors": {},
      "completed_at": "2026-06-25T12:42:45Z"
    },
    "determinant": {
      "status": "complete",
      "missing": [],
      "errors": {},
      "completed_at": "2026-06-25T12:42:46Z"
    },
    "diagram": {
      "status": "complete",
      "missing": [],
      "errors": {},
      "completed_at": "2026-06-25T12:42:46Z"
    },
    "differential equation": {
      "status": "complete",
      "missing": [],
      "errors": {},
      "completed_at": "2026-06-25T12:44:09Z"
    },
    "direction": {
      "status": "complete",
      "missing": [],
      "errors": {},
      "completed_at": "2026-06-25T12:44:10Z"
    },
    "directrix": {
      "status": "complete",
      "missing": [],
      "errors": {},
      "completed_at": "2026-06-25T12:44:11Z"
    },
    "discontinuity": {
      "status": "complete",
      "missing": [],
      "errors": {},
      "completed_at": "2026-06-25T12:44:53Z"
    },
    "discrete random variable": {
      "status": "complete",
      "missing": [],
      "errors": {},
      "completed_at": "2026-06-25T12:46:17Z"
    },
    "displacement": {
      "status": "complete",
      "missing": [],
      "errors": {},
      "completed_at": "2026-06-25T12:47:25Z"
    },
    "displacement vector": {
      "status": "complete",
      "missing": [],
      "errors": {},
      "completed_at": "2026-06-25T12:48:48Z"
    },
    "distance formula": {
      "status": "complete",
      "missing": [],
      "errors": {},
      "completed_at": "2026-06-25T12:48:49Z"
    },
    "distance from point to line": {
      "status": "complete",
      "missing": [],
      "errors": {},
      "completed_at": "2026-06-25T12:50:17Z"
    },
    "diverge": {
      "status": "complete",
      "missing": [],
      "errors": {},
      "completed_at": "2026-06-25T12:50:17Z"
    },
    "domain": {
      "status": "complete",
      "missing": [],
      "errors": {},
      "completed_at": "2026-06-25T12:50:18Z"
    },
    "dot product": {
      "status": "complete",
      "missing": [],
      "errors": {},
      "completed_at": "2026-06-25T12:50:18Z"
    },
    "double angle formula": {
      "status": "complete",
      "missing": [],
      "errors": {},
      "completed_at": "2026-06-25T12:51:02Z"
    },
    "eccentricity": {
      "status": "complete",
      "missing": [],
      "errors": {},
      "completed_at": "2026-06-25T12:52:17Z"
    },
    "element of matrix": {
      "status": "complete",
      "missing": [],
      "errors": {},
      "completed_at": "2026-06-25T12:53:29Z"
    },
    "ellipse": {
      "status": "complete",
      "missing": [],
      "errors": {},
      "completed_at": "2026-06-25T12:55:29Z"
    },
    "enlargement matrix": {
      "status": "complete",
      "missing": [],
      "errors": {},
      "completed_at": "2026-06-25T12:57:27Z"
    },
    "equation of circle": {
      "status": "complete",
      "missing": [],
      "errors": {},
      "completed_at": "2026-06-25T12:57:27Z"
    },
    "equation of plane": {
      "status": "complete",
      "missing": [],
      "errors": {},
      "completed_at": "2026-06-25T12:58:59Z"
    },
    "equation of straight line": {
      "status": "complete",
      "missing": [],
      "errors": {},
      "completed_at": "2026-06-25T12:59:00Z"
    },
    "estimate": {
      "status": "complete",
      "missing": [],
      "errors": {},
      "completed_at": "2026-06-25T12:59:01Z"
    },
    "expectation": {
      "status": "complete",
      "missing": [],
      "errors": {},
      "completed_at": "2026-06-25T12:59:01Z"
    },
    "expected value": {
      "status": "complete",
      "missing": [],
      "errors": {},
      "completed_at": "2026-06-25T12:59:02Z"
    },
    "exponential function": {
      "status": "complete",
      "missing": [],
      "errors": {},
      "completed_at": "2026-06-25T12:59:35Z"
    },
    "first derivative test": {
      "status": "complete",
      "missing": [],
      "errors": {},
      "completed_at": "2026-06-25T13:00:49Z"
    },
    "focus": {
      "status": "complete",
      "missing": [],
      "errors": {},
      "completed_at": "2026-06-25T13:00:49Z"
    },
    "function notation": {
      "status": "complete",
      "missing": [],
      "errors": {},
      "completed_at": "2026-06-25T13:02:00Z"
    },
    "fundamental theorem of calculus": {
      "status": "complete",
      "missing": [],
      "errors": {},
      "completed_at": "2026-06-25T13:03:18Z"
    },
    "general solution": {
      "status": "complete",
      "missing": [],
      "errors": {},
      "completed_at": "2026-06-25T13:05:11Z"
    },
    "geometric series": {
      "status": "complete",
      "missing": [],
      "errors": {},
      "completed_at": "2026-06-25T13:06:51Z"
    },
    "gradient function": {
      "status": "complete",
      "missing": [],
      "errors": {},
      "completed_at": "2026-06-25T13:08:24Z"
    },
    "gradient of tangent": {
      "status": "complete",
      "missing": [],
      "errors": {},
      "completed_at": "2026-06-25T13:09:36Z"
    },
    "graph transformation": {
      "status": "complete",
      "missing": [],
      "errors": {},
      "completed_at": "2026-06-25T13:14:19Z"
    },
    "growth model": {
      "status": "complete",
      "missing": [],
      "errors": {},
      "completed_at": "2026-06-25T13:16:27Z"
    },
    "horizontal asymptote": {
      "status": "complete",
      "missing": [],
      "errors": {},
      "completed_at": "2026-06-25T13:16:27Z"
    },
    "hyperbola": {
      "status": "complete",
      "missing": [],
      "errors": {},
      "completed_at": "2026-06-25T13:17:38Z"
    },
    "identity matrix": {
      "status": "complete",
      "missing": [],
      "errors": {},
      "completed_at": "2026-06-25T13:20:03Z"
    },
    "imaginary part": {
      "status": "complete",
      "missing": [],
      "errors": {},
      "completed_at": "2026-06-25T13:21:29Z"
    },
    "imaginary unit": {
      "status": "complete",
      "missing": [],
      "errors": {},
      "completed_at": "2026-06-25T13:24:44Z"
    },
    "implicit differentiation": {
      "status": "complete",
      "missing": [],
      "errors": {},
      "completed_at": "2026-06-25T13:28:37Z"
    },
    "indefinite integral": {
      "status": "complete",
      "missing": [],
      "errors": {},
      "completed_at": "2026-06-25T13:28:37Z"
    },
    "independent event": {
      "status": "complete",
      "missing": [],
      "errors": {},
      "completed_at": "2026-06-25T13:28:38Z"
    },
    "inductive step": {
      "status": "complete",
      "missing": [],
      "errors": {},
      "completed_at": "2026-06-25T13:31:09Z"
    },
    "infinite limit": {
      "status": "complete",
      "missing": [],
      "errors": {},
      "completed_at": "2026-06-25T13:31:10Z"
    },
    "integration by parts": {
      "status": "complete",
      "missing": [],
      "errors": {},
      "completed_at": "2026-06-25T13:34:13Z"
    },
    "integration by substitution": {
      "status": "complete",
      "missing": [],
      "errors": {},
      "completed_at": "2026-06-25T13:35:32Z"
    },
    "integration constant": {
      "status": "complete",
      "missing": [],
      "errors": {},
      "completed_at": "2026-06-25T13:35:32Z"
    },
    "interpret result": {
      "status": "complete",
      "missing": [],
      "errors": {},
      "completed_at": "2026-06-25T13:35:33Z"
    },
    "interquartile range": {
      "status": "complete",
      "missing": [],
      "errors": {},
      "completed_at": "2026-06-25T13:35:33Z"
    },
    "intersection of curves": {
      "status": "complete",
      "missing": [],
      "errors": {},
      "completed_at": "2026-06-25T13:35:34Z"
    },
    "invariant point": {
      "status": "complete",
      "missing": [],
      "errors": {},
      "completed_at": "2026-06-25T13:35:34Z"
    },
    "inverse function": {
      "status": "complete",
      "missing": [],
      "errors": {},
      "completed_at": "2026-06-25T13:35:35Z"
    },
    "inverse matrix": {
      "status": "complete",
      "missing": [],
      "errors": {},
      "completed_at": "2026-06-25T13:35:36Z"
    },
    "justify": {
      "status": "complete",
      "missing": [],
      "errors": {},
      "completed_at": "2026-06-25T13:35:36Z"
    },
    "kinematics": {
      "status": "complete",
      "missing": [],
      "errors": {},
      "completed_at": "2026-06-25T13:37:07Z"
    },
    "left-hand limit": {
      "status": "complete",
      "missing": [],
      "errors": {},
      "completed_at": "2026-06-25T13:37:07Z"
    },
    "limit at infinity": {
      "status": "complete",
      "missing": [],
      "errors": {},
      "completed_at": "2026-06-25T13:37:49Z"
    },
    "limits of integration": {
      "status": "complete",
      "missing": [],
      "errors": {},
      "completed_at": "2026-06-25T13:38:46Z"
    },
    "line of best fit": {
      "status": "complete",
      "missing": [],
      "errors": {},
      "completed_at": "2026-06-25T13:38:46Z"
    },
    "local maximum": {
      "status": "complete",
      "missing": [],
      "errors": {},
      "completed_at": "2026-06-25T13:40:09Z"
    },
    "local minimum": {
      "status": "complete",
      "missing": [],
      "errors": {},
      "completed_at": "2026-06-25T13:41:44Z"
    },
    "locus": {
      "status": "complete",
      "missing": [],
      "errors": {},
      "completed_at": "2026-06-25T13:41:45Z"
    },
    "locus in complex plane": {
      "status": "complete",
      "missing": [],
      "errors": {},
      "completed_at": "2026-06-25T13:43:52Z"
    },
    "logarithm law": {
      "status": "complete",
      "missing": [],
      "errors": {},
      "completed_at": "2026-06-25T13:43:53Z"
    },
    "logarithmic function": {
      "status": "complete",
      "missing": [],
      "errors": {},
      "completed_at": "2026-06-25T13:45:39Z"
    },
    "lower bound": {
      "status": "complete",
      "missing": [],
      "errors": {},
      "completed_at": "2026-06-25T13:45:40Z"
    },
    "lower limit": {
      "status": "complete",
      "missing": [],
      "errors": {},
      "completed_at": "2026-06-25T13:49:57Z"
    },
    "magnitude": {
      "status": "complete",
      "missing": [],
      "errors": {},
      "completed_at": "2026-06-25T13:49:58Z"
    },
    "mathematical induction": {
      "status": "complete",
      "missing": [],
      "errors": {},
      "completed_at": "2026-06-25T13:53:47Z"
    },
    "matrix": {
      "status": "complete",
      "missing": [],
      "errors": {},
      "completed_at": "2026-06-25T13:53:47Z"
    },
    "matrix multiplication": {
      "status": "complete",
      "missing": [],
      "errors": {},
      "completed_at": "2026-06-25T13:53:48Z"
    },
    "mean": {
      "status": "complete",
      "missing": [],
      "errors": {},
      "completed_at": "2026-06-25T13:53:49Z"
    },
    "median": {
      "status": "complete",
      "missing": [],
      "errors": {},
      "completed_at": "2026-06-25T13:53:49Z"
    },
    "method": {
      "status": "complete",
      "missing": [],
      "errors": {},
      "completed_at": "2026-06-25T13:53:50Z"
    },
    "midpoint": {
      "status": "complete",
      "missing": [],
      "errors": {},
      "completed_at": "2026-06-25T13:53:50Z"
    },
    "mode": {
      "status": "complete",
      "missing": [],
      "errors": {},
      "completed_at": "2026-06-25T13:53:51Z"
    },
    "modelling assumption": {
      "status": "complete",
      "missing": [],
      "errors": {},
      "completed_at": "2026-06-25T13:55:09Z"
    },
    "modulus-argument form": {
      "status": "complete",
      "missing": [],
      "errors": {},
      "completed_at": "2026-06-25T13:56:51Z"
    },
    "multiplication rule": {
      "status": "complete",
      "missing": [],
      "errors": {},
      "completed_at": "2026-06-25T13:57:48Z"
    },
    "mutually exclusive": {
      "status": "complete",
      "missing": [],
      "errors": {},
      "completed_at": "2026-06-25T13:57:49Z"
    },
    "natural exponential": {
      "status": "complete",
      "missing": [],
      "errors": {},
      "completed_at": "2026-06-25T14:00:55Z"
    },
    "natural logarithm": {
      "status": "complete",
      "missing": [],
      "errors": {},
      "completed_at": "2026-06-25T14:02:54Z"
    },
    "negative correlation": {
      "status": "complete",
      "missing": [],
      "errors": {},
      "completed_at": "2026-06-25T14:02:54Z"
    },
    "normal line": {
      "status": "complete",
      "missing": [],
      "errors": {},
      "completed_at": "2026-06-25T14:05:56Z"
    },
    "normal vector": {
      "status": "complete",
      "missing": [],
      "errors": {},
      "completed_at": "2026-06-25T14:08:31Z"
    },
    "null hypothesis": {
      "status": "complete",
      "missing": [],
      "errors": {},
      "completed_at": "2026-06-25T14:08:32Z"
    },
    "optimization": {
      "status": "complete",
      "missing": [],
      "errors": {},
      "completed_at": "2026-06-25T14:12:07Z"
    },
    "order of matrix": {
      "status": "complete",
      "missing": [],
      "errors": {},
      "completed_at": "2026-06-25T14:13:25Z"
    },
    "p-value": {
      "status": "complete",
      "missing": [],
      "errors": {},
      "completed_at": "2026-06-25T14:15:01Z"
    },
    "parabola": {
      "status": "complete",
      "missing": [],
      "errors": {},
      "completed_at": "2026-06-25T14:21:28Z"
    },
    "parallel vector": {
      "status": "complete",
      "missing": [],
      "errors": {},
      "completed_at": "2026-06-25T14:21:29Z"
    },
    "parameter": {
      "status": "complete",
      "missing": [],
      "errors": {},
      "completed_at": "2026-06-25T14:22:16Z"
    },
    "parametric form": {
      "status": "complete",
      "missing": [],
      "errors": {},
      "completed_at": "2026-06-25T14:27:38Z"
    },
    "period": {
      "status": "complete",
      "missing": [],
      "errors": {},
      "completed_at": "2026-06-25T14:27:39Z"
    },
    "perpendicular vector": {
      "status": "complete",
      "missing": [],
      "errors": {},
      "completed_at": "2026-06-25T14:29:01Z"
    },
    "piecewise function": {
      "status": "complete",
      "missing": [],
      "errors": {},
      "completed_at": "2026-06-25T14:31:23Z"
    },
    "point of inflection": {
      "status": "complete",
      "missing": [],
      "errors": {},
      "completed_at": "2026-06-25T14:33:00Z"
    },
    "poisson distribution": {
      "status": "complete",
      "missing": [],
      "errors": {},
      "completed_at": "2026-06-25T14:34:38Z"
    },
    "polar coordinates": {
      "status": "complete",
      "missing": [],
      "errors": {},
      "completed_at": "2026-06-25T14:35:42Z"
    },
    "polar equation": {
      "status": "complete",
      "missing": [],
      "errors": {},
      "completed_at": "2026-06-25T14:38:11Z"
    },
    "polar form": {
      "status": "complete",
      "missing": [],
      "errors": {},
      "completed_at": "2026-06-25T14:39:31Z"
    },
    "population": {
      "status": "complete",
      "missing": [],
      "errors": {},
      "completed_at": "2026-06-25T14:39:32Z"
    },
    "position vector": {
      "status": "complete",
      "missing": [],
      "errors": {},
      "completed_at": "2026-06-25T14:39:32Z"
    },
    "positive correlation": {
      "status": "complete",
      "missing": [],
      "errors": {},
      "completed_at": "2026-06-25T14:39:33Z"
    },
    "power rule": {
      "status": "complete",
      "missing": [],
      "errors": {},
      "completed_at": "2026-06-25T14:39:33Z"
    },
    "principal value": {
      "status": "complete",
      "missing": [],
      "errors": {},
      "completed_at": "2026-06-25T14:39:34Z"
    },
    "probability density function": {
      "status": "complete",
      "missing": [],
      "errors": {},
      "completed_at": "2026-06-25T14:40:18Z"
    },
    "probability distribution": {
      "status": "complete",
      "missing": [],
      "errors": {},
      "completed_at": "2026-06-25T14:41:09Z"
    },
    "probability mass function": {
      "status": "complete",
      "missing": [],
      "errors": {},
      "completed_at": "2026-06-25T14:42:39Z"
    },
    "problem solving": {
      "status": "complete",
      "missing": [],
      "errors": {},
      "completed_at": "2026-06-25T14:42:40Z"
    },
    "product rule": {
      "status": "complete",
      "missing": [],
      "errors": {},
      "completed_at": "2026-06-25T14:45:18Z"
    },
    "product-to-sum formula": {
      "status": "complete",
      "missing": [],
      "errors": {},
      "completed_at": "2026-06-25T14:47:54Z"
    },
    "projection": {
      "status": "complete",
      "missing": [],
      "errors": {},
      "completed_at": "2026-06-25T14:49:55Z"
    },
    "proof": {
      "status": "complete",
      "missing": [],
      "errors": {},
      "completed_at": "2026-06-25T14:49:55Z"
    },
    "property": {
      "status": "complete",
      "missing": [],
      "errors": {},
      "completed_at": "2026-06-25T14:49:56Z"
    },
    "pythagorean identity": {
      "status": "complete",
      "missing": [],
      "errors": {},
      "completed_at": "2026-06-25T14:49:56Z"
    },
    "quadratic equation with complex roots": {
      "status": "complete",
      "missing": [],
      "errors": {},
      "completed_at": "2026-06-25T14:52:17Z"
    },
    "quotient rule": {
      "status": "complete",
      "missing": [],
      "errors": {},
      "completed_at": "2026-06-25T14:53:01Z"
    },
    "r-formula": {
      "status": "complete",
      "missing": [],
      "errors": {},
      "completed_at": "2026-06-25T14:55:01Z"
    },
    "radian measure": {
      "status": "complete",
      "missing": [],
      "errors": {},
      "completed_at": "2026-06-25T14:55:54Z"
    },
    "random variable": {
      "status": "complete",
      "missing": [],
      "errors": {},
      "completed_at": "2026-06-25T14:59:21Z"
    },
    "range": {
      "status": "complete",
      "missing": [],
      "errors": {},
      "completed_at": "2026-06-25T14:59:22Z"
    },
    "rate of change": {
      "status": "complete",
      "missing": [],
      "errors": {},
      "completed_at": "2026-06-25T14:59:22Z"
    },
    "real part": {
      "status": "complete",
      "missing": [],
      "errors": {},
      "completed_at": "2026-06-25T15:02:09Z"
    },
    "reasonableness": {
      "status": "complete",
      "missing": [],
      "errors": {},
      "completed_at": "2026-06-25T15:02:10Z"
    },
    "reasoning": {
      "status": "complete",
      "missing": [],
      "errors": {},
      "completed_at": "2026-06-25T15:02:10Z"
    },
    "reflection matrix": {
      "status": "complete",
      "missing": [],
      "errors": {},
      "completed_at": "2026-06-25T15:04:25Z"
    },
    "regression line": {
      "status": "complete",
      "missing": [],
      "errors": {},
      "completed_at": "2026-06-25T15:05:37Z"
    },
    "related rate": {
      "status": "complete",
      "missing": [],
      "errors": {},
      "completed_at": "2026-06-25T15:06:39Z"
    },
    "removable discontinuity": {
      "status": "complete",
      "missing": [],
      "errors": {},
      "completed_at": "2026-06-25T15:07:28Z"
    },
    "residual": {
      "status": "complete",
      "missing": [],
      "errors": {},
      "completed_at": "2026-06-25T15:13:47Z"
    },
    "resultant vector": {
      "status": "complete",
      "missing": [],
      "errors": {},
      "completed_at": "2026-06-25T15:13:47Z"
    },
    "right-hand limit": {
      "status": "complete",
      "missing": [],
      "errors": {},
      "completed_at": "2026-06-25T15:14:13Z"
    },
    "root of complex number": {
      "status": "complete",
      "missing": [],
      "errors": {},
      "completed_at": "2026-06-25T15:16:17Z"
    },
    "rotation matrix": {
      "status": "complete",
      "missing": [],
      "errors": {},
      "completed_at": "2026-06-25T15:18:20Z"
    },
    "round off": {
      "status": "complete",
      "missing": [],
      "errors": {},
      "completed_at": "2026-06-25T15:18:20Z"
    },
    "sample": {
      "status": "complete",
      "missing": [],
      "errors": {},
      "completed_at": "2026-06-25T15:18:21Z"
    },
    "sampling": {
      "status": "complete",
      "missing": [],
      "errors": {},
      "completed_at": "2026-06-25T15:18:58Z"
    },
    "scalar": {
      "status": "complete",
      "missing": [],
      "errors": {},
      "completed_at": "2026-06-25T15:18:59Z"
    },
    "scalar multiplication": {
      "status": "complete",
      "missing": [],
      "errors": {},
      "completed_at": "2026-06-25T15:18:59Z"
    },
    "scale factor": {
      "status": "complete",
      "missing": [],
      "errors": {},
      "completed_at": "2026-06-25T15:19:00Z"
    },
    "scatter diagram": {
      "status": "complete",
      "missing": [],
      "errors": {},
      "completed_at": "2026-06-25T15:19:01Z"
    },
    "second derivative test": {
      "status": "complete",
      "missing": [],
      "errors": {},
      "completed_at": "2026-06-25T15:24:49Z"
    },
    "separation of variables": {
      "status": "complete",
      "missing": [],
      "errors": {},
      "completed_at": "2026-06-25T15:28:01Z"
    },
    "sigma notation": {
      "status": "complete",
      "missing": [],
      "errors": {},
      "completed_at": "2026-06-25T15:28:01Z"
    },
    "significance level": {
      "status": "complete",
      "missing": [],
      "errors": {},
      "completed_at": "2026-06-25T15:28:02Z"
    },
    "significant figure": {
      "status": "complete",
      "missing": [],
      "errors": {},
      "completed_at": "2026-06-25T15:28:02Z"
    },
    "sine graph": {
      "status": "complete",
      "missing": [],
      "errors": {},
      "completed_at": "2026-06-25T15:28:03Z"
    },
    "sketch": {
      "status": "complete",
      "missing": [],
      "errors": {},
      "completed_at": "2026-06-25T15:28:03Z"
    },
    "sketch curve": {
      "status": "complete",
      "missing": [],
      "errors": {},
      "completed_at": "2026-06-25T15:29:16Z"
    },
    "solution steps": {
      "status": "complete",
      "missing": [],
      "errors": {},
      "completed_at": "2026-06-25T15:29:17Z"
    },
    "standard normal distribution": {
      "status": "complete",
      "missing": [],
      "errors": {},
      "completed_at": "2026-06-25T15:29:17Z"
    },
    "standard score": {
      "status": "complete",
      "missing": [],
      "errors": {},
      "completed_at": "2026-06-25T15:29:18Z"
    },
    "statistic": {
      "status": "complete",
      "missing": [],
      "errors": {},
      "completed_at": "2026-06-25T15:29:19Z"
    },
    "strategy": {
      "status": "complete",
      "missing": [],
      "errors": {},
      "completed_at": "2026-06-25T15:29:19Z"
    },
    "subtraction of vectors": {
      "status": "complete",
      "missing": [],
      "errors": {},
      "completed_at": "2026-06-25T15:29:20Z"
    },
    "sum to infinity": {
      "status": "complete",
      "missing": [],
      "errors": {},
      "completed_at": "2026-06-25T15:33:46Z"
    },
    "sum-to-product formula": {
      "status": "complete",
      "missing": [],
      "errors": {},
      "completed_at": "2026-06-25T15:34:44Z"
    },
    "system of linear equations": {
      "status": "complete",
      "missing": [],
      "errors": {},
      "completed_at": "2026-06-25T15:37:41Z"
    },
    "tangent graph": {
      "status": "complete",
      "missing": [],
      "errors": {},
      "completed_at": "2026-06-25T15:37:42Z"
    },
    "tangent line": {
      "status": "complete",
      "missing": [],
      "errors": {},
      "completed_at": "2026-06-25T15:38:41Z"
    },
    "tangent to circle": {
      "status": "complete",
      "missing": [],
      "errors": {},
      "completed_at": "2026-06-25T15:38:42Z"
    },
    "theorem": {
      "status": "complete",
      "missing": [],
      "errors": {},
      "completed_at": "2026-06-25T15:38:43Z"
    },
    "total distance": {
      "status": "complete",
      "missing": [],
      "errors": {},
      "completed_at": "2026-06-25T15:40:42Z"
    },
    "transformation matrix": {
      "status": "complete",
      "missing": [],
      "errors": {},
      "completed_at": "2026-06-25T15:42:51Z"
    },
    "transpose": {
      "status": "complete",
      "missing": [],
      "errors": {},
      "completed_at": "2026-06-25T15:43:36Z"
    },
    "tree diagram": {
      "status": "complete",
      "missing": [],
      "errors": {},
      "completed_at": "2026-06-25T15:43:37Z"
    },
    "trigonometric equation": {
      "status": "complete",
      "missing": [],
      "errors": {},
      "completed_at": "2026-06-25T15:44:54Z"
    },
    "trigonometric identity": {
      "status": "complete",
      "missing": [],
      "errors": {},
      "completed_at": "2026-06-25T15:44:54Z"
    },
    "type i error": {
      "status": "complete",
      "missing": [],
      "errors": {},
      "completed_at": "2026-06-25T15:46:14Z"
    },
    "type ii error": {
      "status": "complete",
      "missing": [],
      "errors": {},
      "completed_at": "2026-06-25T15:48:33Z"
    },
    "unit circle": {
      "status": "complete",
      "missing": [],
      "errors": {},
      "completed_at": "2026-06-25T15:48:34Z"
    },
    "unit vector": {
      "status": "complete",
      "missing": [],
      "errors": {},
      "completed_at": "2026-06-25T15:48:34Z"
    },
    "upper bound": {
      "status": "complete",
      "missing": [],
      "errors": {},
      "completed_at": "2026-06-25T15:48:35Z"
    },
    "upper limit": {
      "status": "complete",
      "missing": [],
      "errors": {},
      "completed_at": "2026-06-25T15:48:35Z"
    },
    "variance": {
      "status": "complete",
      "missing": [],
      "errors": {},
      "completed_at": "2026-06-25T15:48:36Z"
    },
    "vector": {
      "status": "complete",
      "missing": [],
      "errors": {},
      "completed_at": "2026-06-25T15:48:36Z"
    },
    "vector equation of line": {
      "status": "complete",
      "missing": [],
      "errors": {},
      "completed_at": "2026-06-25T15:50:25Z"
    },
    "velocity": {
      "status": "complete",
      "missing": [],
      "errors": {},
      "completed_at": "2026-06-25T15:50:25Z"
    },
    "vertical asymptote": {
      "status": "complete",
      "missing": [],
      "errors": {},
      "completed_at": "2026-06-25T15:50:26Z"
    },
    "volume of revolution": {
      "status": "complete",
      "missing": [],
      "errors": {},
      "completed_at": "2026-06-25T15:51:32Z"
    },
    "working": {
      "status": "complete",
      "missing": [],
      "errors": {},
      "completed_at": "2026-06-25T15:51:32Z"
    },
    "z-score": {
      "status": "complete",
      "missing": [],
      "errors": {},
      "completed_at": "2026-06-25T15:52:19Z"
    }
  }
}
